vandyck_pycalculator/Binomialdistribution.py
vandyck_pycalculator/Distribution.py
vandyck_pycalculator/Gaussiandistribution.py
vandyck_pycalculator/Generaldistribution.py
vandyck_pycalculator/__init__.py
vancalculator-0.0.2.1.dist-info/LICENSE
vancalculator-0.0.2.1.dist-info/METADATA
vancalculator-0.0.2.1.dist-info/WHEEL
vancalculator-0.0.2.1.dist-info/top_level.txt
vancalculator-0.0.2.1.dist-info/RECORD
