Metadata-Version: 2.1
Name: vancalculator
Version: 0.0.2.1
Summary: Mode, Median, Gaussian and Binomial distributions
Home-page: https://github.com/Laikaiyong/Vandyck-Pycalculate-Package
Author: Vandyck Lai Kai Yong
Author-email: vandycklai@gmail.com
License: UNKNOWN
Project-URL: Bug Tracker, https://github.com/Laikaiyong/Vandyck-Pycalculator-Package/issues
Platform: UNKNOWN
Classifier: Programming Language :: Python :: 3
Classifier: License :: OSI Approved :: MIT License
Classifier: Operating System :: OS Independent
Requires-Python: >=3.9
License-File: LICENSE
